LICENSE
MANIFEST.in
README.md
setup.py
config/roles.conf
config/sqlbridge.conf
sqlbridge/__init__.py
sqlbridge.egg-info/PKG-INFO
sqlbridge.egg-info/SOURCES.txt
sqlbridge.egg-info/dependency_links.txt
sqlbridge.egg-info/entry_points.txt
sqlbridge.egg-info/requires.txt
sqlbridge.egg-info/top_level.txt
sqlbridge.egg-info/zip-safe
sqlbridge/scripts/__init__.py
sqlbridge/scripts/basicrouter.py
sqlbridge/scripts/cli.py
sqlbridge/scripts/client.py
sqlbridge/twisted/__init__.py
sqlbridge/twisted/dbengine.py
sqlbridge/twisted/db/__init__.py
sqlbridge/twisted/db/ausqlite3.py
sqlbridge/twisted/db/dbbase.py
sqlbridge/twisted/db/mysql.py
sqlbridge/twisted/db/postgres.py